ontologysim/__init__.py
ontologysim/Flask/FlaskApp.py
ontologysim/Flask/FlaskMain.py
ontologysim/Flask/__init__.py
ontologysim/Flask/Actions/APIAction.py
ontologysim/Flask/Actions/CommentIdAction.py
ontologysim/Flask/Actions/ComponentAction.py
ontologysim/Flask/Actions/GetIdsAction.py
ontologysim/Flask/Actions/ResetBEAction.py
ontologysim/Flask/Actions/TestAction.py
ontologysim/Flask/Actions/__init__.py
ontologysim/Flask/Actions/CheckProductType/ProcessAction.py
ontologysim/Flask/Actions/CheckProductType/__init__.py
ontologysim/Flask/Actions/CheckProduction/ProductionAction.py
ontologysim/Flask/Actions/CheckProduction/__init__.py
ontologysim/Flask/Actions/DataBase/ConnectDataBaseAction.py
ontologysim/Flask/Actions/DataBase/GetSimulationRunAction.py
ontologysim/Flask/Actions/DataBase/__init__.py
ontologysim/Flask/Actions/Simulation/EventAction.py
ontologysim/Flask/Actions/Simulation/KPIAction.py
ontologysim/Flask/Actions/Simulation/KPIListAction.py
ontologysim/Flask/Actions/Simulation/OwlDonwloadAction.py
ontologysim/Flask/Actions/Simulation/RunSimulationAction.py
ontologysim/Flask/Actions/Simulation/SimulationLoadAction.py
ontologysim/Flask/Actions/Simulation/StartAction.py
ontologysim/Flask/Actions/Simulation/StartUntilTimeAction.py
ontologysim/Flask/Actions/Simulation/__init__.py
ontologysim/Flask/Actions/UtilMethods/ProductionDict.py
ontologysim/Flask/Actions/UtilMethods/StateStorage.py
ontologysim/Flask/Actions/UtilMethods/__init__.py
ontologysim/Flask/Assets/__init__.py
ontologysim/Flask/Assets/DefaultSaveFolder/__init__.py
ontologysim/Flask/instance/__init__.py
ontologysim/Flask/instance/config.py
ontologysim/ProductionSimulation/__init__.py
ontologysim/ProductionSimulation/analyse/TimeAnalyse.py
ontologysim/ProductionSimulation/analyse/__init__.py
ontologysim/ProductionSimulation/controller/__init__.py
ontologysim/ProductionSimulation/controller/machine_controller/MachineController.py
ontologysim-1.0.1.dist-info/LICENSE
ontologysim-1.0.1.dist-info/METADATA
ontologysim-1.0.1.dist-info/WHEEL
ontologysim-1.0.1.dist-info/top_level.txt
ontologysim-1.0.1.dist-info/RECORD
