Metadata-Version: 2.1
Name: ontologysim
Version: 1.0.1
Summary: UNKNOWN
Home-page: https://github.com/larsKiefer/ontologysim
Author: Lars Kiefer, Marvin Carl May
Author-email: lars.kiefer@alumni.kit.edu
License: GPLv3
Project-URL: Documentation, https://ontologysim.readthedocs.io/en/latest/
Project-URL: Frontend, https://github.com/larsKiefer/ontologysim_react
Keywords: ontology,manufacturing,simulation
Platform: UNKNOWN
Classifier: Natural Language :: English
Classifier: Topic :: Scientific/Engineering
Classifier: Programming Language :: Python :: 3
Classifier: Programming Language :: Python :: 3.7
Classifier: Programming Language :: Python :: 3.8
Requires-Python: >=3.7
License-File: LICENSE
Requires-Dist: rdflib (==5.0.0)
Requires-Dist: numpy (==1.17.3)
Requires-Dist: pandas (==1.0.3)
Requires-Dist: requests (==2.24.0)
Requires-Dist: Cython (==0.29.21)
Requires-Dist: pyodbc (==4.0.30)
Requires-Dist: owlready2 (==0.34)
Requires-Dist: matplotlib (==3.3.2)
Requires-Dist: flask
Requires-Dist: redis
Requires-Dist: flask-cors
Requires-Dist: flask-swagger-ui
Requires-Dist: SQLAlchemy
Requires-Dist: flask-sqlalchemy
Requires-Dist: Deprecated
Requires-Dist: recommonmark
Requires-Dist: python-decouple (==3.4)
Requires-Dist: jwt
Requires-Dist: pyjwt
Requires-Dist: bcrypt
Requires-Dist: sphinx-rtd-theme
Requires-Dist: sphinx-markdown-tables
